tahoe_x1/__init__.py
tahoe_x1/_version.py
tahoe_x1/loss.py
tahoe_x1/py.typed
tahoe_x1/data/__init__.py
tahoe_x1/data/collator.py
tahoe_x1/data/dataloader.py
tahoe_x1/model/__init__.py
tahoe_x1/model/blocks.py
tahoe_x1/model/model.py
tahoe_x1/tasks/__init__.py
tahoe_x1/tasks/cell_classification.py
tahoe_x1/tasks/emb_extractor.py
tahoe_x1/tasks/marginal_essentiality.py
tahoe_x1/tokenizer/__init__.py
tahoe_x1/tokenizer/gene_tokenizer.py
tahoe_x1/utils/__init__.py
tahoe_x1/utils/s3_utils.py
tahoe_x1/utils/util.py
tahoe_x1-1.0.0.dist-info/licenses/LICENSE
tahoe_x1-1.0.0.dist-info/METADATA
tahoe_x1-1.0.0.dist-info/WHEEL
tahoe_x1-1.0.0.dist-info/top_level.txt
tahoe_x1-1.0.0.dist-info/RECORD
