Metadata-Version: 2.4
Name: tahoe-x1
Version: 1.0.0
Summary: Tahoe-x1: Perturbation trained single-cell foundation models with up to 3 billion parameters
Home-page: https://github.com/tahoebio/tahoe-x1/
Author: Tahoe Therapeutics
Author-email: admin@tahoebio.ai
License: Apache-2.0
Project-URL: Homepage, https://github.com/tahoebio/tahoe-x1
Project-URL: Documentation, https://github.com/tahoebio/tahoe-x1#readme
Project-URL: Repository, https://github.com/tahoebio/tahoe-x1
Project-URL: Bug Tracker, https://github.com/tahoebio/tahoe-x1/issues
Project-URL: Model Card, https://huggingface.co/tahoebio/Tahoe-x1
Project-URL: Paper, http://www.tahoebio.ai/news/tahoe-x1
Keywords: single-cell,foundation-model,genomics,transcriptomics,perturbation,machine-learning,deep-learning
Classifier: Development Status :: 4 - Beta
Classifier: Intended Audience :: Science/Research
Classifier: License :: OSI Approved :: Apache Software License
Classifier: Programming Language :: Python :: 3
Classifier: Programming Language :: Python :: 3.10
Classifier: Programming Language :: Python :: 3.11
Classifier: Topic :: Scientific/Engineering :: Artificial Intelligence
Classifier: Topic :: Scientific/Engineering :: Bio-Informatics
Requires-Python: >=3.10
License-File: LICENSE
Requires-Dist: awscli<2.0,>=1.32
Requires-Dist: llm-foundry[gpu]<1.0,>=0.17.1
Requires-Dist: mosaicml-streaming<1.0,>=0.7.0
Requires-Dist: torch<3.0,>=2.5.0
Requires-Dist: scanpy<2.0,>=1.9.0
Provides-Extra: dev
Requires-Dist: pre-commit<4,>=3.4.0; extra == "dev"
Requires-Dist: toml<0.11,>=0.10.2; extra == "dev"
Requires-Dist: ipykernel; extra == "dev"
Requires-Dist: packaging<23,>=21; extra == "dev"
Provides-Extra: all
Requires-Dist: ipykernel; extra == "all"
Requires-Dist: packaging<23,>=21; extra == "all"
Requires-Dist: pre-commit<4,>=3.4.0; extra == "all"
Requires-Dist: toml<0.11,>=0.10.2; extra == "all"
Dynamic: author
Dynamic: author-email
Dynamic: classifier
Dynamic: description
Dynamic: description-content-type
Dynamic: home-page
Dynamic: keywords
Dynamic: license
Dynamic: license-file
Dynamic: project-url
Dynamic: provides-extra
Dynamic: requires-dist
Dynamic: requires-python
Dynamic: summary
